{
  "plugin": {
    "totalDownloads": 63,
    "stargazers": 0,
    "createdAt": "2026-01-05T11:27:50Z",
    "latestReleaseAt": "2026-01-10T14:12:42Z",
    "lastCommitDate": "2026-01-10T14:11:03Z",
    "commitCountInLast24Months": 14,
    "totalReleases": 6,
    "releases": [
      {
        "publishedAt": "2026-01-07T05:46:22Z",
        "downloads": 2
      },
      {
        "publishedAt": "2026-01-06T15:29:20Z",
        "downloads": 0
      },
      {
        "publishedAt": "2026-01-07T05:28:55Z",
        "downloads": 1
      },
      {
        "publishedAt": "2026-01-07T05:46:58Z",
        "downloads": 1
      },
      {
        "publishedAt": "2026-01-07T06:41:50Z",
        "downloads": 10
      },
      {
        "publishedAt": "2026-01-10T14:12:42Z",
        "downloads": 49
      }
    ],
    "openIssues": [],
    "closedIssues": [],
    "openPRs": [],
    "closedPRs": [],
    "mergedPRs": []
  },
  "now": "2026-04-30T01:26:17.016Z"
}