{
  "plugin": {
    "totalDownloads": 150,
    "stargazers": 2,
    "createdAt": "2026-02-22T03:10:40Z",
    "latestReleaseAt": "2026-02-23T15:05:32Z",
    "lastCommitDate": "2026-03-06T02:05:51Z",
    "commitCountInLast24Months": 10,
    "totalReleases": 2,
    "releases": [
      {
        "publishedAt": "2026-02-22T04:26:46Z",
        "downloads": 5
      },
      {
        "publishedAt": "2026-02-23T15:05:32Z",
        "downloads": 145
      }
    ],
    "openIssues": [
      {
        "label": "bug",
        "createdAt": "2026-03-04T08:28:56Z"
      }
    ],
    "closedIssues": [],
    "openPRs": [],
    "closedPRs": [],
    "mergedPRs": []
  },
  "now": "2026-04-30T01:28:24.964Z"
}