{
  "plugin": {
    "totalDownloads": 20,
    "stargazers": 1,
    "createdAt": "2026-03-23T07:54:20Z",
    "latestReleaseAt": "2026-03-23T08:24:45Z",
    "lastCommitDate": "2026-03-25T08:34:44Z",
    "commitCountInLast24Months": 14,
    "totalReleases": 1,
    "releases": [
      {
        "publishedAt": "2026-03-23T08:24:45Z",
        "downloads": 20
      }
    ],
    "openIssues": [],
    "closedIssues": [],
    "openPRs": [],
    "closedPRs": [],
    "mergedPRs": []
  },
  "now": "2026-04-30T01:33:28.915Z"
}