{
  "plugin": {
    "totalDownloads": 46,
    "stargazers": 1,
    "createdAt": "2026-03-02T13:38:33Z",
    "latestReleaseAt": "2026-03-04T07:20:54Z",
    "lastCommitDate": "2026-03-04T07:20:54Z",
    "commitCountInLast24Months": 5,
    "totalReleases": 1,
    "releases": [
      {
        "publishedAt": "2026-03-04T07:20:54Z",
        "downloads": 46
      }
    ],
    "openIssues": [],
    "closedIssues": [],
    "openPRs": [],
    "closedPRs": [],
    "mergedPRs": []
  },
  "now": "2026-04-30T01:33:46.702Z"
}